bashgpt/__init__.py
bashgpt/chat.py
bashgpt/db_and_key.py
bashgpt/defaults.json
bashgpt/extract_text.py
bashgpt/get_file.py
bashgpt/load_defaults.py
bashgpt/main.py
bashgpt/models.json
bashgpt/modes.json
bashgpt/modes_and_models.py
bashgpt/terminal_codes.py
bashgpt/util_functions.py
bashgpt/whisper.py
bashgptZ-1.0.1.data/data/defaults.json
bashgptZ-1.0.1.data/data/models.json
bashgptZ-1.0.1.data/data/modes.json
bashgptZ-1.0.1.dist-info/LICENSE.txt
bashgptZ-1.0.1.dist-info/METADATA
bashgptZ-1.0.1.dist-info/WHEEL
bashgptZ-1.0.1.dist-info/entry_points.txt
bashgptZ-1.0.1.dist-info/top_level.txt
bashgptZ-1.0.1.dist-info/RECORD
