Metadata-Version: 2.1
Name: bashgptZ
Version: 1.0.1
Project-URL: Homepage, https://github.com/yourusername/bashgpt
Project-URL: Bug Tracker, https://github.com/yourusername/bashgpt/issues
Classifier: Programming Language :: Python :: 3
Classifier: License :: OSI Approved :: MIT License
Classifier: Operating System :: OS Independent
Requires-Python: >=3.7
License-File: LICENSE.txt
Requires-Dist: openai >=1.12.0
Requires-Dist: anthropic >=0.19.1
Requires-Dist: PyAudio >=0.2.13
